sideko_allium/README.md
sideko_allium/__init__.py
sideko_allium/client.py
sideko_allium/core/__init__.py
sideko_allium/core/api_error.py
sideko_allium/core/auth.py
sideko_allium/core/base_client.py
sideko_allium/core/binary_response.py
sideko_allium/core/query.py
sideko_allium/core/request.py
sideko_allium/core/response.py
sideko_allium/core/type_utils.py
sideko_allium/core/utils.py
sideko_allium/environment.py
sideko_allium/resources/admin/README.md
sideko_allium/resources/admin/__init__.py
sideko_allium/resources/admin/client.py
sideko_allium/resources/admin/data_transformations/README.md
sideko_allium/resources/admin/data_transformations/__init__.py
sideko_allium/resources/admin/data_transformations/client.py
sideko_allium/resources/developer/README.md
sideko_allium/resources/developer/__init__.py
sideko_allium/resources/developer/bitcoin/README.md
sideko_allium/resources/developer/bitcoin/__init__.py
sideko_allium/resources/developer/bitcoin/client.py
sideko_allium/resources/developer/bitcoin/mempool/README.md
sideko_allium/resources/developer/bitcoin/mempool/__init__.py
sideko_allium/resources/developer/bitcoin/mempool/client.py
sideko_allium/resources/developer/bitcoin/mempool/inputs/README.md
sideko_allium/resources/developer/bitcoin/mempool/inputs/__init__.py
sideko_allium/resources/developer/bitcoin/mempool/inputs/client.py
sideko_allium/resources/developer/bitcoin/mempool/outputs/README.md
sideko_allium/resources/developer/bitcoin/mempool/outputs/__init__.py
sideko_allium/resources/developer/bitcoin/mempool/outputs/client.py
sideko_allium/resources/developer/bitcoin/mempool/transactions/README.md
sideko_allium/resources/developer/bitcoin/mempool/transactions/__init__.py
sideko_allium/resources/developer/bitcoin/mempool/transactions/client.py
sideko_allium/resources/developer/bitcoin/ordinals/README.md
sideko_allium/resources/developer/bitcoin/ordinals/__init__.py
sideko_allium/resources/developer/bitcoin/ordinals/client.py
sideko_allium-0.1.0.dist-info/METADATA
sideko_allium-0.1.0.dist-info/WHEEL
sideko_allium-0.1.0.dist-info/RECORD
